acho/__init__.py
acho/version.py
acho/client/__init__.py
acho/client/app_client.py
acho/client/app_sockets.py
acho/client/client_utils.py
acho/client/http_client.py
acho/client/project_client.py
acho/client/socket_client.py
acho/client/studio_client.py
acho/client/view_client.py
acho_sdk-0.3.13.dist-info/METADATA
acho_sdk-0.3.13.dist-info/WHEEL
acho_sdk-0.3.13.dist-info/top_level.txt
acho_sdk-0.3.13.dist-info/RECORD
