Metadata-Version: 2.2
Name: acho_sdk
Version: 0.3.13
Summary: Acho Python SDK
Author-email: Timothy Zhang <timothy@acho.io>
License: MIT
Classifier: Programming Language :: Python :: 3
Classifier: Operating System :: OS Independent
Requires-Python: >=3.7
Requires-Dist: python-socketio==5.9.0
Requires-Dist: requests==2.25.1
Requires-Dist: setuptools
Requires-Dist: subprocess32; python_version < "3.2"
Requires-Dist: ipynbname
Requires-Dist: python-engineio>=3.11.2
Requires-Dist: pandas>=1.0.0
Requires-Dist: aiohttp
Requires-Dist: aiofiles
Requires-Dist: requests-toolbelt
